invariant_sdk/__init__.py
invariant_sdk/cli.py
invariant_sdk/crystal.py
invariant_sdk/engine.py
invariant_sdk/export.py
invariant_sdk/halo.py
invariant_sdk/mcp_server.py
invariant_sdk/merkle.py
invariant_sdk/overlay.py
invariant_sdk/physics.py
invariant_sdk/tokenize.py
invariant_sdk/ui.py
invariant_sdk/ui_handler.py
invariant_sdk/ui_pages.py
invariant_sdk/ui_server.py
invarianthub-1.4.2.dist-info/METADATA
invarianthub-1.4.2.dist-info/WHEEL
invarianthub-1.4.2.dist-info/entry_points.txt
invarianthub-1.4.2.dist-info/top_level.txt
invarianthub-1.4.2.dist-info/RECORD
