Metadata-Version: 2.4
Name: invarianthub
Version: 1.4.2
Summary: Deterministic Knowledge Engine - Semantic Kernel for LLM Agents
License: MIT
Requires-Python: >=3.9
Requires-Dist: httpx>=0.24.0
Requires-Dist: pathspec>=0.11.0
Provides-Extra: embeddings
Requires-Dist: sentence-transformers>=2.2.0; extra == "embeddings"
Provides-Extra: dev
Requires-Dist: pytest; extra == "dev"
Requires-Dist: maturin; extra == "dev"
